jekyll_manager/__main__.py
jekyll_manager/exceptions.py
jekyll_manager/manager.py
jekyll_manager/post.py
jekyll_manager/utils.py
jekyll_manager-1.2.0.dist-info/METADATA
jekyll_manager-1.2.0.dist-info/WHEEL
jekyll_manager-1.2.0.dist-info/entry_points.txt
jekyll_manager-1.2.0.dist-info/top_level.txt
jekyll_manager-1.2.0.dist-info/RECORD
