Metadata-Version: 2.1
Name: jekyll-manager
Version: 1.2.0
Summary: A command line interface for managing your Jekyll Blog
Home-page: https://github.com/kludron/jekyll-manager
Author: Kludron
Author-email: kludron@lukewarmsecurityinfo.com
Requires-Dist: pyyaml
Requires-Dist: colorama
Requires-Dist: python-frontmatter
